ru/__init__.py
ru/config/__init__.py
ru/constants/__init__.py
ru/constants/constants.py
ru/exceptions/__init__.py
ru/exceptions/exceptions.py
ru/hints/__init__.py
ru/logger/__init__.py
ru/selenium_utils/__init__.py
ru/utils/__init__.py
raccy_utils-0.4.2.dist-info/METADATA
raccy_utils-0.4.2.dist-info/WHEEL
raccy_utils-0.4.2.dist-info/top_level.txt
raccy_utils-0.4.2.dist-info/RECORD
