Metadata-Version: 2.1
Name: raccy-utils
Version: 0.4.2
Summary: A collection of utility functions, and classes.
Home-page: https://github.com/danielafriyie/raccy-utils
Author: Daniel Afriyie
Author-email: danielafriyie98@gmail.com
License: Apache License, Version 2.0
Platform: UNKNOWN
Classifier: Programming Language :: Python
Classifier: Programming Language :: Python :: 3.7
Classifier: Programming Language :: Python :: 3.8
Classifier: Programming Language :: Python :: 3.9
Classifier: Intended Audience :: Developers
Classifier: Operating System :: OS Independent
Classifier: Topic :: Software Development :: Libraries :: Application Frameworks
Classifier: Topic :: Software Development :: Libraries :: Python Modules
Classifier: Development Status :: 5 - Production/Stable
Requires-Python: >=3.7
Requires-Dist: colorama
Requires-Dist: pyperclip
